{
  "list": [
    {
      "rootPath": "",
      "text": "< Back to Home",
      "href": "../../"
    },
    {
      "rootPath": "",
      "text": "Code"
    },
    {
      "rootPath": "",
      "text": "Git",
      "href": "?t=git",
      "data": ["git.md"]
    },
    {
      "rootPath": "",
      "text": "React",
      "href": "?t=react",
      "data": ["react.md"]
    },
    {
      "rootPath": "",
      "text": "Css Page Layout",
      "href": "?t=cspglo",
      "data": ["css-page-layout.md"]
    },
{
      "rootPath": "",
      "text": "Typescript",
      "href": "?t=ts",
      "data": ["ts.md"]
    }
  ]
}
